darkseid/__init__.py
darkseid/comic.py
darkseid/issue_string.py
darkseid/utils.py
darkseid/validate.py
darkseid/archivers/__init__.py
darkseid/archivers/archiver.py
darkseid/archivers/factory.py
darkseid/archivers/pdf.py
darkseid/archivers/rar.py
darkseid/archivers/sevenzip.py
darkseid/archivers/tar.py
darkseid/archivers/zip.py
darkseid/metadata/__init__.py
darkseid/metadata/base_handler.py
darkseid/metadata/comicinfo.py
darkseid/metadata/data_classes.py
darkseid/metadata/metroninfo.py
darkseid/schemas/ComicInfo/v1/ComicInfo.xsd
darkseid/schemas/ComicInfo/v2/ComicInfo.xsd
darkseid/schemas/MetronInfo/v1/MetronInfo.xsd
darkseid-7.2.2.dist-info/METADATA
darkseid-7.2.2.dist-info/WHEEL
darkseid-7.2.2.dist-info/licenses/LICENSE
darkseid-7.2.2.dist-info/RECORD
