Metadata-Version: 2.4
Name: darkseid
Version: 7.2.2
Summary: A library to interact with comic archives
Project-URL: Homepage, https://github.com/Metron-Project/darkseid
Project-URL: Bug Tracker, https://github.com/Metron-Project/darkseid/issues
Author-email: Brian Pepple <bpepple@metron.cloud>
Maintainer-email: Brian Pepple <bpepple@metron.cloud>
License-Expression: GPL-3.0-or-later
License-File: LICENSE
Keywords: cb7,cbr,cbt,cbz,comic,comicinfo,metadata,metroninfo,pdf
Classifier: Development Status :: 5 - Production/Stable
Classifier: Intended Audience :: Developers
Classifier: Natural Language :: English
Classifier: Operating System :: MacOS :: MacOS X
Classifier: Operating System :: Microsoft :: Windows
Classifier: Operating System :: POSIX
Classifier: Operating System :: POSIX :: BSD
Classifier: Operating System :: POSIX :: Linux
Classifier: Programming Language :: Python :: 3.10
Classifier: Programming Language :: Python :: 3.11
Classifier: Programming Language :: Python :: 3.12
Classifier: Programming Language :: Python :: 3.13
Classifier: Programming Language :: Python :: 3.14
Classifier: Topic :: Software Development :: Libraries
Classifier: Topic :: Utilities
Requires-Python: >=3.10
Requires-Dist: defusedxml<0.8,>=0.7.1
Requires-Dist: natsort<9,>=8.0.0
Requires-Dist: pycountry<25,>=24.6.1
Requires-Dist: rarfile>=4.2
Requires-Dist: xmlschema>=4
Requires-Dist: zipremove>=0.8.0
Provides-Extra: 7zip
Requires-Dist: py7zr>=1.0.0; extra == '7zip'
Provides-Extra: pdf
Requires-Dist: pymupdf>=1.26.6; extra == 'pdf'
Provides-Extra: pillow
Requires-Dist: pillow>=11.3.0; extra == 'pillow'
